valle_6steps/__init__.py
valle_6steps-0.0.3.dist-info/LICENSE
valle_6steps-0.0.3.dist-info/METADATA
valle_6steps-0.0.3.dist-info/WHEEL
valle_6steps-0.0.3.dist-info/top_level.txt
valle_6steps-0.0.3.dist-info/RECORD
