Metadata-Version: 2.1
Name: valle-6steps
Version: 0.0.3
Summary: This project helps writing and pronunciation in English
Home-page: https://github.com/pypa/sampleproject
Author: Ilenia Valle
Author-email: IValle@unibz.it
License: UNKNOWN
Project-URL: Bug Tracker, https://github.com/pypa/sampleproject/issues
Platform: UNKNOWN
Classifier: Programming Language :: Python :: 3
Classifier: License :: OSI Approved :: MIT License
Classifier: Operating System :: OS Independent
Requires-Python: >=3.6
